geoguessr_async/__init__.py
geoguessr_async/geo_utils.py
geoguessr_async/geoguessr.py
geoguessr_async/models.py
geoguessr_async-1.0.13.dist-info/METADATA
geoguessr_async-1.0.13.dist-info/WHEEL
geoguessr_async-1.0.13.dist-info/licenses/LICENSE
geoguessr_async-1.0.13.dist-info/RECORD
