Metadata-Version: 2.4
Name: geoguessr_async
Version: 1.0.13
Summary: An asynchronous API integrator for Geoguessr
Project-URL: Homepage, https://github.com/toinoublz/geoguessr_async
Author-email: Antoine BLAISE <antoine.blaise34@gmail.com>
License-File: LICENSE
Classifier: License :: OSI Approved :: MIT License
Classifier: Operating System :: OS Independent
Classifier: Programming Language :: Python :: 3
Requires-Python: >=3.9
Requires-Dist: aiohttp>=3.8.5
